mantis/__init__.py
mantis/easy_openai/__init__.py
mantis/easy_openai/openai_utils.py
mantis/mllm_tools/__init__.py
mantis/mllm_tools/blip_flant5_eval.py
mantis/mllm_tools/cogvlm_eval.py
mantis/mllm_tools/emu2_eval.py
mantis/mllm_tools/fuyu_eval.py
mantis/mllm_tools/gpt4v_eval.py
mantis/mllm_tools/idefics1_eval.py
mantis/mllm_tools/idefics2_eval.py
mantis/mllm_tools/idefics3_eval.py
mantis/mllm_tools/instructblip_eval.py
mantis/mllm_tools/kosmos2_eval.py
mantis/mllm_tools/llava_eval.py
mantis/mllm_tools/llava_next_eval.py
mantis/mllm_tools/mfuyu_eval.py
mantis/mllm_tools/minicpmv_eval.py
mantis/mllm_tools/mllava_eval.py
mantis/mllm_tools/mllm_utils.py
mantis/mllm_tools/openflamingo_eval.py
mantis/mllm_tools/otterhd_eval.py
mantis/mllm_tools/otterimage_eval.py
mantis/mllm_tools/ottervideo_eval.py
mantis/mllm_tools/qwenVL_eval.py
mantis/mllm_tools/videollava_eval.py
mantis/mllm_tools/vila_eval.py
mantis/mllm_tools/model_utils/__init__.py
mantis/mllm_tools/model_utils/otter/__init__.py
mantis/mllm_tools/model_utils/otter/base_model.py
mantis/mllm_tools/model_utils/otter/otter_image.py
mantis/mllm_tools/model_utils/otter/otter_video.py
mantis/mllm_tools/model_utils/otter/otterhd.py
mantis/mllm_tools/model_utils/otter/models/__init__.py
mantis/mllm_tools/model_utils/otter/models/falcon/__init__.py
mantis/mllm_tools/model_utils/otter/models/falcon/configuration_RW.py
mantis/mllm_tools/model_utils/otter/models/falcon/modelling_RW.py
mantis/mllm_tools/model_utils/otter/models/flamingo/__init__.py
mantis/mllm_tools/model_utils/otter/models/flamingo/configuration_flamingo.py
mantis/mllm_tools/model_utils/otter/models/flamingo/converting_flamingo_to_bf16.py
mantis/mllm_tools/model_utils/otter/models/flamingo/converting_flamingo_to_hf.py
mantis/mllm_tools/model_utils/otter/models/flamingo/converting_flamingo_to_lora.py
mantis/mllm_tools/model_utils/otter/models/flamingo/injecting_falcon_into_flamingo.py
mantis_vl-0.0.5.dist-info/LICENSE
mantis_vl-0.0.5.dist-info/METADATA
mantis_vl-0.0.5.dist-info/WHEEL
mantis_vl-0.0.5.dist-info/top_level.txt
mantis_vl-0.0.5.dist-info/RECORD
