Metadata-Version: 2.1
Name: mantis-vl
Version: 0.0.5
Summary: Official Codes for of "MANTIS: Interleaved Multi-Image Instruction Tuning"
Home-page: https://github.com/TIGER-AI-Lab/Mantis
Author: Dongfu Jiang
Author-email: dongfu.jiang@uwaterloo.ca
License-File: LICENSE
Requires-Dist: transformers
Requires-Dist: sentencepiece
Requires-Dist: torch
Requires-Dist: Pillow
Requires-Dist: accelerate
Requires-Dist: torchvision
Requires-Dist: datasets ==2.18.0
Provides-Extra: eval
Requires-Dist: tqdm ; extra == 'eval'
Requires-Dist: numpy ; extra == 'eval'
Requires-Dist: prettytable ; extra == 'eval'
Requires-Dist: fire ; extra == 'eval'
Requires-Dist: datasets ==2.18.0 ; extra == 'eval'
Requires-Dist: openai ; extra == 'eval'
Requires-Dist: tiktoken ; extra == 'eval'
Requires-Dist: av ; extra == 'eval'
Requires-Dist: decord ; extra == 'eval'
Provides-Extra: train
Requires-Dist: fire ; extra == 'train'
Requires-Dist: tqdm ; extra == 'train'
Requires-Dist: numpy ; extra == 'train'
Requires-Dist: requests ; extra == 'train'
Requires-Dist: matplotlib ; extra == 'train'
Requires-Dist: transformers-stream-generator ; extra == 'train'
Requires-Dist: tiktoken ; extra == 'train'
Requires-Dist: chardet ; extra == 'train'
Requires-Dist: deepspeed ; extra == 'train'
Requires-Dist: peft >=0.10 ; extra == 'train'
Requires-Dist: bitsandbytes ; extra == 'train'
Requires-Dist: wandb ; extra == 'train'
Requires-Dist: ninja ; extra == 'train'
Requires-Dist: scipy ; extra == 'train'
Requires-Dist: webdataset ; extra == 'train'
Requires-Dist: braceexpand ; extra == 'train'
Requires-Dist: pandas ; extra == 'train'
Requires-Dist: orjson ; extra == 'train'
Requires-Dist: prettytable ; extra == 'train'
Requires-Dist: pytest ; extra == 'train'
Requires-Dist: opencv-python ; extra == 'train'
Requires-Dist: pyarrow ; extra == 'train'
Requires-Dist: dask ; extra == 'train'
Requires-Dist: einops-exts ; extra == 'train'
Requires-Dist: datasets ==2.18.0 ; extra == 'train'
Requires-Dist: open-clip-torch ; extra == 'train'
Requires-Dist: openai ; extra == 'train'
Requires-Dist: av ; extra == 'train'
Requires-Dist: qwen-vl-utils ; extra == 'train'
